declarativeenum/__init__.py
declarativeenum/core.py
declarativeenum/exceptions.py
declarativeenum-1.0.0.dist-info/METADATA
declarativeenum-1.0.0.dist-info/WHEEL
declarativeenum-1.0.0.dist-info/licenses/LICENSE
declarativeenum-1.0.0.dist-info/RECORD
